<?xml version="1.0" encoding="UTF-8" ?>
<!DOCTYPE mapper PUBLIC "-//mybatis.org//DTD Mapper 3.0//EN" "http://mybatis.org/dtd/mybatis-3-mapper.dtd" >
<mapper namespace="pkp.waybillOfflineMapper" >
  <resultMap id="BaseResultMap" type="com.deppon.foss.module.pickup.waybill.shared.domain.WaybillOfflineEntity" >
    <id column="ID" property="id" jdbcType="VARCHAR" />
    <result column="WAYBILL_NO" property="waybillNo" jdbcType="VARCHAR" />
    <result column="ORDER_NO" property="orderNo" jdbcType="VARCHAR" />
    <result column="DELIVERY_CUSTOMER_ID" property="deliveryCustomerId" jdbcType="VARCHAR" />
    <result column="DELIVERY_CUSTOMER_CODE" property="deliveryCustomerCode" jdbcType="VARCHAR" />
    <result column="DELIVERY_CUSTOMER_NAME" property="deliveryCustomerName" jdbcType="VARCHAR" />
    <result column="DELIVERY_CUSTOMER_MOBILEPHONE" property="deliveryCustomerMobilephone" jdbcType="VARCHAR" />
    <result column="DELIVERY_CUSTOMER_PHONE" property="deliveryCustomerPhone" jdbcType="VARCHAR" />
    <result column="DELIVERY_CUSTOMER_CONTACT" property="deliveryCustomerContact" jdbcType="VARCHAR" />
    <result column="DELIVERY_CUSTOMER_NATION_CODE" property="deliveryCustomerNationCode" jdbcType="VARCHAR" />
    <result column="DELIVERY_CUSTOMER_PROV_CODE" property="deliveryCustomerProvCode" jdbcType="VARCHAR" />
    <result column="DELIVERY_CUSTOMER_CITY_CODE" property="deliveryCustomerCityCode" jdbcType="VARCHAR" />
    <result column="DELIVERY_CUSTOMER_DIST_CODE" property="deliveryCustomerDistCode" jdbcType="VARCHAR" />
    <result column="DELIVERY_CUSTOMER_ADDRESS" property="deliveryCustomerAddress" jdbcType="VARCHAR" />
    <result column="RECEIVE_CUSTOMER_ID" property="receiveCustomerId" jdbcType="VARCHAR" />
    <result column="RECEIVE_CUSTOMER_CODE" property="receiveCustomerCode" jdbcType="VARCHAR" />
    <result column="RECEIVE_CUSTOMER_NAME" property="receiveCustomerName" jdbcType="VARCHAR" />
    <result column="RECEIVE_CUSTOMER_MOBILEPHONE" property="receiveCustomerMobilephone" jdbcType="VARCHAR" />
    <result column="RECEIVE_CUSTOMER_PHONE" property="receiveCustomerPhone" jdbcType="VARCHAR" />
    <result column="RECEIVE_CUSTOMER_CONTACT" property="receiveCustomerContact" jdbcType="VARCHAR" />
    <result column="RECEIVE_CUSTOMER_NATION_CODE" property="receiveCustomerNationCode" jdbcType="VARCHAR" />
    <result column="RECEIVE_CUSTOMER_PROV_CODE" property="receiveCustomerProvCode" jdbcType="VARCHAR" />
    <result column="RECEIVE_CUSTOMER_CITY_CODE" property="receiveCustomerCityCode" jdbcType="VARCHAR" />
    <result column="RECEIVE_CUSTOMER_DIST_CODE" property="receiveCustomerDistCode" jdbcType="VARCHAR" />
    <result column="RECEIVE_CUSTOMER_ADDRESS" property="receiveCustomerAddress" jdbcType="VARCHAR" />
    <result column="RECEIVE_ORG_CODE" property="receiveOrgCode" jdbcType="VARCHAR" />
    <result column="PRODUCT_ID" property="productId" jdbcType="VARCHAR" />
    <result column="PRODUCT_CODE" property="productCode" jdbcType="VARCHAR" />
    <result column="RECEIVE_METHOD" property="receiveMethod" jdbcType="VARCHAR" />
    <result column="CUSTOMER_PICKUP_ORG_CODE" property="customerPickupOrgCode" jdbcType="VARCHAR" />
    <result column="LOAD_METHOD" property="loadMethod" jdbcType="VARCHAR" />
    <result column="TARGET_ORG_CODE" property="targetOrgCode" jdbcType="VARCHAR" />
    <result column="PICKUP_TO_DOOR" property="pickupToDoor" jdbcType="CHAR" />
    <result column="DRIVER_CODE" property="driverCode" jdbcType="VARCHAR" />
    <result column="PICKUP_CENTRALIZED" property="pickupCentralized" jdbcType="CHAR" />
    <result column="LOAD_LINE_CODE" property="loadLineCode" jdbcType="VARCHAR" />
    <result column="LOAD_ORG_CODE" property="loadOrgCode" jdbcType="VARCHAR" />
    <result column="LAST_LOAD_ORG_CODE" property="lastLoadOrgCode" jdbcType="VARCHAR" />
    <result column="PRE_DEPARTURE_TIME" property="preDepartureTime" jdbcType="DATE" />
    <result column="PRE_CUSTOMER_PICKUP_TIME" property="preCustomerPickupTime" jdbcType="DATE" />
    <result column="CAR_DIRECT_DELIVERY" property="carDirectDelivery" jdbcType="CHAR" />
    <result column="GOODS_NAME" property="goodsName" jdbcType="VARCHAR" />
    <result column="GOODS_QTY_TOTAL" property="goodsQtyTotal" jdbcType="DECIMAL" />
    <result column="GOODS_WEIGHT_TOTAL" property="goodsWeightTotal" jdbcType="DECIMAL" />
    <result column="GOODS_VOLUME_TOTAL" property="goodsVolumeTotal" jdbcType="DECIMAL" />
    <result column="GOODS_SIZE" property="goodsSize" jdbcType="VARCHAR" />
    <result column="GOODS_TYPE_CODE" property="goodsTypeCode" jdbcType="VARCHAR" />
    <result column="PRECIOUS_GOODS" property="preciousGoods" jdbcType="CHAR" />
    <result column="SPECIAL_SHAPED_GOODS" property="specialShapedGoods" jdbcType="CHAR" />
    <result column="OUTER_NOTES" property="outerNotes" jdbcType="VARCHAR" />
    <result column="INNER_NOTES" property="innerNotes" jdbcType="VARCHAR" />
    <result column="GOODS_PACKAGE" property="goodsPackage" jdbcType="VARCHAR" />
    <result column="INSURANCE_AMOUNT" property="insuranceAmount" jdbcType="DECIMAL" />
    <result column="INSURANCE_RATE" property="insuranceRate" jdbcType="DECIMAL" />
    <result column="INSURANCE_FEE" property="insuranceFee" jdbcType="DECIMAL" />
    <result column="COD_AMOUNT" property="codAmount" jdbcType="DECIMAL" />
    <result column="COD_RATE" property="codRate" jdbcType="DECIMAL" />
    <result column="COD_FEE" property="codFee" jdbcType="DECIMAL" />
    <result column="REFUND_TYPE" property="refundType" jdbcType="VARCHAR" />
    <result column="RETURN_BILL_TYPE" property="returnBillType" jdbcType="VARCHAR" />
    <result column="SECRET_PREPAID" property="secretPrepaid" jdbcType="CHAR" />
    <result column="TO_PAY_AMOUNT" property="toPayAmount" jdbcType="DECIMAL" />
    <result column="PRE_PAY_AMOUNT" property="prePayAmount" jdbcType="DECIMAL" />
    <result column="DELIVERY_GOODS_FEE" property="deliveryGoodsFee" jdbcType="DECIMAL" />
    <result column="OTHER_FEE" property="otherFee" jdbcType="DECIMAL" />
    <result column="PACKAGE_FEE" property="packageFee" jdbcType="DECIMAL" />
    <result column="PROMOTIONS_FEE" property="promotionsFee" jdbcType="DECIMAL" />
    <result column="BILLING_TYPE" property="billingType" jdbcType="VARCHAR" />
    <result column="UNIT_PRICE" property="unitPrice" jdbcType="DECIMAL" />
    <result column="TRANSPORT_FEE" property="transportFee" jdbcType="DECIMAL" />
    <result column="VALUE_ADD_FEE" property="valueAddFee" jdbcType="DECIMAL" />
    <result column="PAID_METHOD" property="paidMethod" jdbcType="VARCHAR" />
    <result column="ARRIVE_TYPE" property="arriveType" jdbcType="VARCHAR" />
    <result column="ACTIVE" property="active" jdbcType="VARCHAR" />
    <result column="FORBIDDEN_LINE" property="forbiddenLine" jdbcType="CHAR" />
    <result column="FREIGHT_METHOD" property="freightMethod" jdbcType="VARCHAR" />
    <result column="FLIGHT_SHIFT" property="flightShift" jdbcType="VARCHAR" />
    <result column="TOTAL_FEE" property="totalFee" jdbcType="DECIMAL" />
    <result column="PROMOTIONS_CODE" property="promotionsCode" jdbcType="VARCHAR" />
    <result column="CREATE_TIME" property="createTime" jdbcType="DATE" />
    <result column="MODIFY_TIME" property="modifyTime" jdbcType="DATE" />
    <result column="BILL_TIME" property="billTime" jdbcType="DATE" />
    <result column="CREATE_USER_CODE" property="createUserCode" jdbcType="VARCHAR" />
    <result column="MODIFY_USER_CODE" property="modifyUserCode" jdbcType="VARCHAR" />
    <result column="CREATE_ORG_CODE" property="createOrgCode" jdbcType="VARCHAR" />
    <result column="MODIFY_ORG_CODE" property="modifyOrgCode" jdbcType="VARCHAR" />
    <result column="REF_ID" property="refId" jdbcType="VARCHAR" />
    <result column="REF_CODE" property="refCode" jdbcType="VARCHAR" />
    <result column="CURRENCY_CODE" property="currencyCode" jdbcType="VARCHAR" />
    <result column="IS_WHOLE_VEHICLE" property="isWholeVehicle" jdbcType="CHAR" />
    <result column="WHOLE_VEHICLE_APPFEE" property="wholeVehicleAppfee" jdbcType="DECIMAL" />
    <result column="WHOLE_VEHICLE_ACTUALFEE" property="wholeVehicleActualfee" jdbcType="DECIMAL" />
    <result column="ACCOUNT_NAME" property="accountName" jdbcType="VARCHAR" />
    <result column="ACCOUNT_CODE" property="accountCode" jdbcType="VARCHAR" />
    <result column="ACCOUNT_BANK" property="accountBank" jdbcType="VARCHAR" />
    <result column="BILL_WEIGHT" property="billWeight" jdbcType="DECIMAL" />
    <result column="PICKUP_FEE" property="pickupFee" jdbcType="DECIMAL" />
    <result column="SERVICE_FEE" property="serviceFee" jdbcType="DECIMAL" />
    <result column="PRE_ARRIVE_TIME" property="preArriveTime" jdbcType="DATE" />
    <result column="TRANSPORT_TYPE" property="transportType" jdbcType="VARCHAR" />
    <result column="ADD_TIME" property="addTime" jdbcType="DATE" />
    <result column="INSURANCE_RATE" property="insuranceRate" jdbcType="DECIMAL" />
    <result column="INSURANCE_FEE" property="insuranceFee" jdbcType="DECIMAL" />
    <result column="UNIT_PRICE" property="unitPrice" jdbcType="DECIMAL" />
    <result column="CONTACT_ADDRESS_ID" property="contactAddressId" jdbcType="VARCHAR" />
    <result column="FLIGHT_NUMBER_TYPE" property="flightNumberType" jdbcType="VARCHAR" />
    <result column="COLLECTION_DEPARTMENT" property="collectionDepartment" jdbcType="VARCHAR" />
    <result column="TRANSPORTATION_REMARK" property="transportationRemark" jdbcType="VARCHAR" />
    <result column="IS_PASS_OWN_DEPARTMENT" property="isPassOwnDepartment" jdbcType="VARCHAR" />
    <result column="PAPER_NUM" property="paperNum" jdbcType="DECIMAL" />
    <result column="WOOD_NUM" property="woodNum" jdbcType="DECIMAL" />
    <result column="FIBRE_NUM" property="fibreNum" jdbcType="DECIMAL" />
    <result column="SALVER_NUM" property="salverNum" jdbcType="DECIMAL" />
    <result column="MEMBRANE_NUM" property="membraneNum" jdbcType="DECIMAL" />
    <result column="OTHER_PACKAGE" property="otherPackage" jdbcType="VARCHAR" />
    <result column="DELIVERY_CUSTOMER_CONTACT_ID" property="deliveryCustomerContactId" jdbcType="VARCHAR" />
    <result column="RECEIVE_CUSTOMER_CONTACT_ID" property="receiveCustomerContactId" jdbcType="VARCHAR" />
    <result column="PENDING_TYPE" property="pendingType" jdbcType="VARCHAR" />
    <result column="LICENSE_PLATE_NUM" property="licensePlateNum" jdbcType="VARCHAR" />
    

  </resultMap>
  <sql id="Base_Column_List" >
    ID, WAYBILL_NO, ORDER_NO, DELIVERY_CUSTOMER_ID, DELIVERY_CUSTOMER_CODE, DELIVERY_CUSTOMER_NAME, 
    DELIVERY_CUSTOMER_MOBILEPHONE, DELIVERY_CUSTOMER_PHONE, DELIVERY_CUSTOMER_CONTACT, 
    DELIVERY_CUSTOMER_NATION_CODE, DELIVERY_CUSTOMER_PROV_CODE, DELIVERY_CUSTOMER_CITY_CODE, 
    DELIVERY_CUSTOMER_DIST_CODE, DELIVERY_CUSTOMER_ADDRESS, RECEIVE_CUSTOMER_ID, RECEIVE_CUSTOMER_CODE, 
    RECEIVE_CUSTOMER_NAME, RECEIVE_CUSTOMER_MOBILEPHONE, RECEIVE_CUSTOMER_PHONE, RECEIVE_CUSTOMER_CONTACT, 
    RECEIVE_CUSTOMER_NATION_CODE, RECEIVE_CUSTOMER_PROV_CODE, RECEIVE_CUSTOMER_CITY_CODE, 
    RECEIVE_CUSTOMER_DIST_CODE, RECEIVE_CUSTOMER_ADDRESS, RECEIVE_ORG_CODE, PRODUCT_ID, 
    PRODUCT_CODE, RECEIVE_METHOD, CUSTOMER_PICKUP_ORG_CODE, LOAD_METHOD, TARGET_ORG_CODE, 
    PICKUP_TO_DOOR, DRIVER_CODE, PICKUP_CENTRALIZED, LOAD_LINE_CODE, LOAD_ORG_CODE, LAST_LOAD_ORG_CODE, 
    PRE_DEPARTURE_TIME, PRE_CUSTOMER_PICKUP_TIME, CAR_DIRECT_DELIVERY, GOODS_NAME, GOODS_QTY_TOTAL, 
    GOODS_WEIGHT_TOTAL, GOODS_VOLUME_TOTAL, GOODS_SIZE, GOODS_TYPE_CODE, PRECIOUS_GOODS, 
    SPECIAL_SHAPED_GOODS, OUTER_NOTES, INNER_NOTES, GOODS_PACKAGE, INSURANCE_AMOUNT, 
    INSURANCE_RATE, INSURANCE_FEE, COD_AMOUNT, COD_RATE, COD_FEE, REFUND_TYPE, RETURN_BILL_TYPE, 
    SECRET_PREPAID, TO_PAY_AMOUNT, PRE_PAY_AMOUNT, DELIVERY_GOODS_FEE, OTHER_FEE, PACKAGE_FEE, 
    PROMOTIONS_FEE, BILLING_TYPE, UNIT_PRICE, TRANSPORT_FEE, VALUE_ADD_FEE, PAID_METHOD, 
    ARRIVE_TYPE, ACTIVE, FORBIDDEN_LINE, FREIGHT_METHOD, FLIGHT_SHIFT, TOTAL_FEE, PROMOTIONS_CODE, 
    CREATE_TIME, MODIFY_TIME, BILL_TIME, CREATE_USER_CODE, MODIFY_USER_CODE, CREATE_ORG_CODE, 
    MODIFY_ORG_CODE, REF_ID, REF_CODE, CURRENCY_CODE, IS_WHOLE_VEHICLE, WHOLE_VEHICLE_APPFEE, 
    WHOLE_VEHICLE_ACTUALFEE, 
    ACCOUNT_NAME, ACCOUNT_CODE, ACCOUNT_BANK, BILL_WEIGHT, PICKUP_FEE, SERVICE_FEE, PRE_ARRIVE_TIME, 
    TRANSPORT_TYPE,ADD_TIME,INSURANCE_RATE,INSURANCE_FEE,UNIT_PRICE,CONTACT_ADDRESS_ID,FLIGHT_NUMBER_TYPE,
    COLLECTION_DEPARTMENT,TRANSPORTATION_REMARK,IS_PASS_OWN_DEPARTMENT,PAPER_NUM,WOOD_NUM,FIBRE_NUM,
    SALVER_NUM,MEMBRANE_NUM,OTHER_PACKAGE,DELIVERY_CUSTOMER_CONTACT_ID,RECEIVE_CUSTOMER_CONTACT_ID,PENDING_TYPE,
    LICENSE_PLATE_NUM 
  </sql>
  
   <select id="selectWaybillLocalByPrimaryKey" resultMap="BaseResultMap" parameterType="java.lang.String" >
    select 
    <include refid="Base_Column_List" />
    from PKP.T_SRV_WAYBILL_OFFLINE
    where ID = #{id,jdbcType=VARCHAR}
  </select>
  
  <select id="selectByWaybillLocalNo" resultMap="BaseResultMap" parameterType="java.lang.String" >
    select 
    <include refid="Base_Column_List" />
    from PKP.T_SRV_WAYBILL_OFFLINE
    where WAYBILL_NO = #{waybillNo,jdbcType=VARCHAR}
  </select>
  
  <select id="selectLastWaybillLocal" resultMap="BaseResultMap" >
    select limit 1 1 
    <include refid="Base_Column_List" />
    from PKP.T_SRV_WAYBILL_OFFLINE
   		order by create_time desc
  </select>
  
  <delete id="deleteWaybillLocalByPrimaryKey" parameterType="java.lang.String" >
    delete from PKP.T_SRV_WAYBILL_OFFLINE
    where ID = #{id,jdbcType=VARCHAR}
  </delete>
   
  <insert id="insertWaybillLocal" parameterType="com.deppon.foss.module.pickup.waybill.shared.domain.WaybillOfflineEntity" >
    insert into PKP.T_SRV_WAYBILL_OFFLINE (ID, WAYBILL_NO, ORDER_NO, 
      DELIVERY_CUSTOMER_ID, DELIVERY_CUSTOMER_CODE, 
      DELIVERY_CUSTOMER_NAME, DELIVERY_CUSTOMER_MOBILEPHONE, 
      DELIVERY_CUSTOMER_PHONE, DELIVERY_CUSTOMER_CONTACT, 
      DELIVERY_CUSTOMER_NATION_CODE, DELIVERY_CUSTOMER_PROV_CODE, 
      DELIVERY_CUSTOMER_CITY_CODE, DELIVERY_CUSTOMER_DIST_CODE, 
      DELIVERY_CUSTOMER_ADDRESS, RECEIVE_CUSTOMER_ID, 
      RECEIVE_CUSTOMER_CODE, RECEIVE_CUSTOMER_NAME, 
      RECEIVE_CUSTOMER_MOBILEPHONE, RECEIVE_CUSTOMER_PHONE, 
      RECEIVE_CUSTOMER_CONTACT, RECEIVE_CUSTOMER_NATION_CODE, 
      RECEIVE_CUSTOMER_PROV_CODE, RECEIVE_CUSTOMER_CITY_CODE, 
      RECEIVE_CUSTOMER_DIST_CODE, RECEIVE_CUSTOMER_ADDRESS, 
      RECEIVE_ORG_CODE, PRODUCT_ID, PRODUCT_CODE, 
      RECEIVE_METHOD, CUSTOMER_PICKUP_ORG_CODE, LOAD_METHOD, 
      TARGET_ORG_CODE, PICKUP_TO_DOOR, DRIVER_CODE, 
      PICKUP_CENTRALIZED, LOAD_LINE_CODE, LOAD_ORG_CODE, 
      LAST_LOAD_ORG_CODE, PRE_DEPARTURE_TIME, PRE_CUSTOMER_PICKUP_TIME, 
      CAR_DIRECT_DELIVERY, GOODS_NAME, GOODS_QTY_TOTAL, 
      GOODS_WEIGHT_TOTAL, GOODS_VOLUME_TOTAL, GOODS_SIZE, 
      GOODS_TYPE_CODE, PRECIOUS_GOODS, SPECIAL_SHAPED_GOODS, 
      OUTER_NOTES, INNER_NOTES, GOODS_PACKAGE, 
      INSURANCE_AMOUNT, INSURANCE_RATE, INSURANCE_FEE, 
      COD_AMOUNT, COD_RATE, COD_FEE, 
      REFUND_TYPE, RETURN_BILL_TYPE, SECRET_PREPAID, 
      TO_PAY_AMOUNT, PRE_PAY_AMOUNT, DELIVERY_GOODS_FEE, 
      OTHER_FEE, PACKAGE_FEE, PROMOTIONS_FEE, 
      BILLING_TYPE, UNIT_PRICE, TRANSPORT_FEE, 
      VALUE_ADD_FEE, PAID_METHOD, ARRIVE_TYPE, 
      ACTIVE, FORBIDDEN_LINE, FREIGHT_METHOD, 
      FLIGHT_SHIFT, TOTAL_FEE, PROMOTIONS_CODE, 
      CREATE_TIME, MODIFY_TIME, BILL_TIME, 
      CREATE_USER_CODE, MODIFY_USER_CODE, CREATE_ORG_CODE, 
      MODIFY_ORG_CODE, REF_ID, REF_CODE, 
      CURRENCY_CODE, IS_WHOLE_VEHICLE, WHOLE_VEHICLE_APPFEE, 
      WHOLE_VEHICLE_ACTUALFEE, ACCOUNT_NAME, 
      ACCOUNT_CODE, ACCOUNT_BANK, BILL_WEIGHT, 
      PICKUP_FEE, SERVICE_FEE, PRE_ARRIVE_TIME, 
      TRANSPORT_TYPE,ADD_TIME,INSURANCE_RATE,INSURANCE_FEE,UNIT_PRICE,
      CONTACT_ADDRESS_ID,FLIGHT_NUMBER_TYPE,COLLECTION_DEPARTMENT,TRANSPORTATION_REMARK,
      IS_PASS_OWN_DEPARTMENT,PAPER_NUM,WOOD_NUM,FIBRE_NUM,SALVER_NUM,MEMBRANE_NUM,
      OTHER_PACKAGE,DELIVERY_CUSTOMER_CONTACT_ID,RECEIVE_CUSTOMER_CONTACT_ID,PENDING_TYPE,
      LICENSE_PLATE_NUM)
    values (#{id,jdbcType=VARCHAR}, #{waybillNo,jdbcType=VARCHAR}, #{orderNo,jdbcType=VARCHAR}, 
      #{deliveryCustomerId,jdbcType=VARCHAR}, #{deliveryCustomerCode,jdbcType=VARCHAR}, 
      #{deliveryCustomerName,jdbcType=VARCHAR}, #{deliveryCustomerMobilephone,jdbcType=VARCHAR}, 
      #{deliveryCustomerPhone,jdbcType=VARCHAR}, #{deliveryCustomerContact,jdbcType=VARCHAR}, 
      #{deliveryCustomerNationCode,jdbcType=VARCHAR}, #{deliveryCustomerProvCode,jdbcType=VARCHAR}, 
      #{deliveryCustomerCityCode,jdbcType=VARCHAR}, #{deliveryCustomerDistCode,jdbcType=VARCHAR}, 
      #{deliveryCustomerAddress,jdbcType=VARCHAR}, #{receiveCustomerId,jdbcType=VARCHAR}, 
      #{receiveCustomerCode,jdbcType=VARCHAR}, #{receiveCustomerName,jdbcType=VARCHAR}, 
      #{receiveCustomerMobilephone,jdbcType=VARCHAR}, #{receiveCustomerPhone,jdbcType=VARCHAR}, 
      #{receiveCustomerContact,jdbcType=VARCHAR}, #{receiveCustomerNationCode,jdbcType=VARCHAR}, 
      #{receiveCustomerProvCode,jdbcType=VARCHAR}, #{receiveCustomerCityCode,jdbcType=VARCHAR}, 
      #{receiveCustomerDistCode,jdbcType=VARCHAR}, #{receiveCustomerAddress,jdbcType=VARCHAR}, 
      #{receiveOrgCode,jdbcType=VARCHAR}, #{productId,jdbcType=VARCHAR}, #{productCode,jdbcType=VARCHAR}, 
      #{receiveMethod,jdbcType=VARCHAR}, #{customerPickupOrgCode,jdbcType=VARCHAR}, #{loadMethod,jdbcType=VARCHAR}, 
      #{targetOrgCode,jdbcType=VARCHAR}, #{pickupToDoor,jdbcType=CHAR}, #{driverCode,jdbcType=VARCHAR}, 
      #{pickupCentralized,jdbcType=CHAR}, #{loadLineCode,jdbcType=VARCHAR}, #{loadOrgCode,jdbcType=VARCHAR}, 
      #{lastLoadOrgCode,jdbcType=VARCHAR}, #{preDepartureTime,jdbcType=DATE}, #{preCustomerPickupTime,jdbcType=DATE}, 
      #{carDirectDelivery,jdbcType=CHAR}, #{goodsName,jdbcType=VARCHAR}, #{goodsQtyTotal,jdbcType=DECIMAL}, 
      #{goodsWeightTotal,jdbcType=DECIMAL}, #{goodsVolumeTotal,jdbcType=DECIMAL}, #{goodsSize,jdbcType=VARCHAR}, 
      #{goodsTypeCode,jdbcType=VARCHAR}, #{preciousGoods,jdbcType=CHAR}, #{specialShapedGoods,jdbcType=CHAR}, 
      #{outerNotes,jdbcType=VARCHAR}, #{innerNotes,jdbcType=VARCHAR}, #{goodsPackage,jdbcType=VARCHAR}, 
      #{insuranceAmount,jdbcType=DECIMAL}, #{insuranceRate,jdbcType=DECIMAL}, #{insuranceFee,jdbcType=DECIMAL}, 
      #{codAmount,jdbcType=DECIMAL}, #{codRate,jdbcType=DECIMAL}, #{codFee,jdbcType=DECIMAL}, 
      #{refundType,jdbcType=VARCHAR}, #{returnBillType,jdbcType=VARCHAR}, #{secretPrepaid,jdbcType=CHAR}, 
      #{toPayAmount,jdbcType=DECIMAL}, #{prePayAmount,jdbcType=DECIMAL}, #{deliveryGoodsFee,jdbcType=DECIMAL}, 
      #{otherFee,jdbcType=DECIMAL}, #{packageFee,jdbcType=DECIMAL}, #{promotionsFee,jdbcType=DECIMAL}, 
      #{billingType,jdbcType=VARCHAR}, #{unitPrice,jdbcType=DECIMAL}, #{transportFee,jdbcType=DECIMAL}, 
      #{valueAddFee,jdbcType=DECIMAL}, #{paidMethod,jdbcType=VARCHAR}, #{arriveType,jdbcType=VARCHAR}, 
      #{active,jdbcType=VARCHAR}, #{forbiddenLine,jdbcType=CHAR}, #{freightMethod,jdbcType=VARCHAR}, 
      #{flightShift,jdbcType=VARCHAR}, #{totalFee,jdbcType=DECIMAL}, #{promotionsCode,jdbcType=VARCHAR}, 
      #{createTime,jdbcType=DATE}, #{modifyTime,jdbcType=DATE}, #{billTime,jdbcType=DATE}, 
      #{createUserCode,jdbcType=VARCHAR}, #{modifyUserCode,jdbcType=VARCHAR}, #{createOrgCode,jdbcType=VARCHAR}, 
      #{modifyOrgCode,jdbcType=VARCHAR}, #{refId,jdbcType=VARCHAR}, #{refCode,jdbcType=VARCHAR}, 
      #{currencyCode,jdbcType=VARCHAR}, #{isWholeVehicle,jdbcType=CHAR}, #{wholeVehicleAppfee,jdbcType=DECIMAL}, 
      #{wholeVehicleActualfee,jdbcType=DECIMAL}, #{accountName,jdbcType=VARCHAR}, 
      #{accountCode,jdbcType=VARCHAR}, #{accountBank,jdbcType=VARCHAR}, #{billWeight,jdbcType=DECIMAL}, 
      #{pickupFee,jdbcType=DECIMAL}, #{serviceFee,jdbcType=DECIMAL}, #{preArriveTime,jdbcType=DATE}, 
      #{insuranceRate,jdbcType=DECIMAL},#{insuranceFee,jdbcType=DECIMAL},
      #{unitPrice,jdbcType=DECIMAL},#{contactAddressId,jdbcType=VARCHAR},
      #{flightNumberType,jdbcType=VARCHAR},#{collectionDepartment,jdbcType=VARCHAR},
 	  #{transportationRemark,jdbcType=VARCHAR},#{isPassOwnDepartment,jdbcType=VARCHAR},	
 	  #{paperNum,jdbcType=DECIMAL},#{woodNum,jdbcType=DECIMAL},	
 	  #{fibreNum,jdbcType=DECIMAL},#{salverNum,jdbcType=DECIMAL},		
 	  #{membraneNum,jdbcType=DECIMAL},#{otherPackage,jdbcType=VARCHAR},	
 	  #{deliveryCustomerContactId,jdbcType=VARCHAR},#{receiveCustomerContactId,jdbcType=VARCHAR},	
      #{pendingType,jdbcType=VARCHAR},#{licensePlateNum,jdbcType=VARCHAR})
  </insert>
  <insert id="insertSelective" parameterType="com.deppon.foss.module.pickup.waybill.shared.domain.WaybillOfflineEntity" >
    insert into PKP.T_SRV_WAYBILL_OFFLINE
    <trim prefix="(" suffix=")" suffixOverrides="," >
      <if test="id != null" >
        ID,
      </if>
      <if test="waybillNo != null" >
        WAYBILL_NO,
      </if>
      <if test="orderNo != null" >
        ORDER_NO,
      </if>
      <if test="deliveryCustomerId != null" >
        DELIVERY_CUSTOMER_ID,
      </if>
      <if test="deliveryCustomerCode != null" >
        DELIVERY_CUSTOMER_CODE,
      </if>
      <if test="deliveryCustomerName != null" >
        DELIVERY_CUSTOMER_NAME,
      </if>
      <if test="deliveryCustomerMobilephone != null" >
        DELIVERY_CUSTOMER_MOBILEPHONE,
      </if>
      <if test="deliveryCustomerPhone != null" >
        DELIVERY_CUSTOMER_PHONE,
      </if>
      <if test="deliveryCustomerContact != null" >
        DELIVERY_CUSTOMER_CONTACT,
      </if>
      <if test="deliveryCustomerNationCode != null" >
        DELIVERY_CUSTOMER_NATION_CODE,
      </if>
      <if test="deliveryCustomerProvCode != null" >
        DELIVERY_CUSTOMER_PROV_CODE,
      </if>
      <if test="deliveryCustomerCityCode != null" >
        DELIVERY_CUSTOMER_CITY_CODE,
      </if>
      <if test="deliveryCustomerDistCode != null" >
        DELIVERY_CUSTOMER_DIST_CODE,
      </if>
      <if test="deliveryCustomerAddress != null" >
        DELIVERY_CUSTOMER_ADDRESS,
      </if>
      <if test="receiveCustomerId != null" >
        RECEIVE_CUSTOMER_ID,
      </if>
      <if test="receiveCustomerCode != null" >
        RECEIVE_CUSTOMER_CODE,
      </if>
      <if test="receiveCustomerName != null" >
        RECEIVE_CUSTOMER_NAME,
      </if>
      <if test="receiveCustomerMobilephone != null" >
        RECEIVE_CUSTOMER_MOBILEPHONE,
      </if>
      <if test="receiveCustomerPhone != null" >
        RECEIVE_CUSTOMER_PHONE,
      </if>
      <if test="receiveCustomerContact != null" >
        RECEIVE_CUSTOMER_CONTACT,
      </if>
      <if test="receiveCustomerNationCode != null" >
        RECEIVE_CUSTOMER_NATION_CODE,
      </if>
      <if test="receiveCustomerProvCode != null" >
        RECEIVE_CUSTOMER_PROV_CODE,
      </if>
      <if test="receiveCustomerCityCode != null" >
        RECEIVE_CUSTOMER_CITY_CODE,
      </if>
      <if test="receiveCustomerDistCode != null" >
        RECEIVE_CUSTOMER_DIST_CODE,
      </if>
      <if test="receiveCustomerAddress != null" >
        RECEIVE_CUSTOMER_ADDRESS,
      </if>
      <if test="receiveOrgCode != null" >
        RECEIVE_ORG_CODE,
      </if>
      <if test="productId != null" >
        PRODUCT_ID,
      </if>
      <if test="productCode != null" >
        PRODUCT_CODE,
      </if>
      <if test="receiveMethod != null" >
        RECEIVE_METHOD,
      </if>
      <if test="customerPickupOrgCode != null" >
        CUSTOMER_PICKUP_ORG_CODE,
      </if>
      <if test="loadMethod != null" >
        LOAD_METHOD,
      </if>
      <if test="targetOrgCode != null" >
        TARGET_ORG_CODE,
      </if>
      <if test="pickupToDoor != null" >
        PICKUP_TO_DOOR,
      </if>
      <if test="driverCode != null" >
        DRIVER_CODE,
      </if>
      <if test="pickupCentralized != null" >
        PICKUP_CENTRALIZED,
      </if>
      <if test="loadLineCode != null" >
        LOAD_LINE_CODE,
      </if>
      <if test="loadOrgCode != null" >
        LOAD_ORG_CODE,
      </if>
      <if test="lastLoadOrgCode != null" >
        LAST_LOAD_ORG_CODE,
      </if>
      <if test="preDepartureTime != null" >
        PRE_DEPARTURE_TIME,
      </if>
      <if test="preCustomerPickupTime != null" >
        PRE_CUSTOMER_PICKUP_TIME,
      </if>
      <if test="carDirectDelivery != null" >
        CAR_DIRECT_DELIVERY,
      </if>
      <if test="goodsName != null" >
        GOODS_NAME,
      </if>
      <if test="goodsQtyTotal != null" >
        GOODS_QTY_TOTAL,
      </if>
      <if test="goodsWeightTotal != null" >
        GOODS_WEIGHT_TOTAL,
      </if>
      <if test="goodsVolumeTotal != null" >
        GOODS_VOLUME_TOTAL,
      </if>
      <if test="goodsSize != null" >
        GOODS_SIZE,
      </if>
      <if test="goodsTypeCode != null" >
        GOODS_TYPE_CODE,
      </if>
      <if test="preciousGoods != null" >
        PRECIOUS_GOODS,
      </if>
      <if test="specialShapedGoods != null" >
        SPECIAL_SHAPED_GOODS,
      </if>
      <if test="outerNotes != null" >
        OUTER_NOTES,
      </if>
      <if test="innerNotes != null" >
        INNER_NOTES,
      </if>
      <if test="goodsPackage != null" >
        GOODS_PACKAGE,
      </if>
      <if test="insuranceAmount != null" >
        INSURANCE_AMOUNT,
      </if>
      <if test="insuranceRate != null" >
        INSURANCE_RATE,
      </if>
      <if test="insuranceFee != null" >
        INSURANCE_FEE,
      </if>
      <if test="codAmount != null" >
        COD_AMOUNT,
      </if>
      <if test="codRate != null" >
        COD_RATE,
      </if>
      <if test="codFee != null" >
        COD_FEE,
      </if>
      <if test="refundType != null" >
        REFUND_TYPE,
      </if>
      <if test="returnBillType != null" >
        RETURN_BILL_TYPE,
      </if>
      <if test="secretPrepaid != null" >
        SECRET_PREPAID,
      </if>
      <if test="toPayAmount != null" >
        TO_PAY_AMOUNT,
      </if>
      <if test="prePayAmount != null" >
        PRE_PAY_AMOUNT,
      </if>
      <if test="deliveryGoodsFee != null" >
        DELIVERY_GOODS_FEE,
      </if>
      <if test="otherFee != null" >
        OTHER_FEE,
      </if>
      <if test="packageFee != null" >
        PACKAGE_FEE,
      </if>
      <if test="promotionsFee != null" >
        PROMOTIONS_FEE,
      </if>
      <if test="billingType != null" >
        BILLING_TYPE,
      </if>
      <if test="unitPrice != null" >
        UNIT_PRICE,
      </if>
      <if test="transportFee != null" >
        TRANSPORT_FEE,
      </if>
      <if test="valueAddFee != null" >
        VALUE_ADD_FEE,
      </if>
      <if test="paidMethod != null" >
        PAID_METHOD,
      </if>
      <if test="arriveType != null" >
        ARRIVE_TYPE,
      </if>
      <if test="active != null" >
        ACTIVE,
      </if>
      <if test="forbiddenLine != null" >
        FORBIDDEN_LINE,
      </if>
      <if test="freightMethod != null" >
        FREIGHT_METHOD,
      </if>
      <if test="flightShift != null" >
        FLIGHT_SHIFT,
      </if>
      <if test="totalFee != null" >
        TOTAL_FEE,
      </if>
      <if test="promotionsCode != null" >
        PROMOTIONS_CODE,
      </if>
      <if test="createTime != null" >
        CREATE_TIME,
      </if>
      <if test="modifyTime != null" >
        MODIFY_TIME,
      </if>
      <if test="billTime != null" >
        BILL_TIME,
      </if>
      <if test="createUserCode != null" >
        CREATE_USER_CODE,
      </if>
      <if test="modifyUserCode != null" >
        MODIFY_USER_CODE,
      </if>
      <if test="createOrgCode != null" >
        CREATE_ORG_CODE,
      </if>
      <if test="modifyOrgCode != null" >
        MODIFY_ORG_CODE,
      </if>
      <if test="refId != null" >
        REF_ID,
      </if>
      <if test="refCode != null" >
        REF_CODE,
      </if>
      <if test="currencyCode != null" >
        CURRENCY_CODE,
      </if>
      <if test="isWholeVehicle != null" >
        IS_WHOLE_VEHICLE,
      </if>
      <if test="wholeVehicleAppfee != null" >
        WHOLE_VEHICLE_APPFEE,
      </if>
      <if test="wholeVehicleActualfee != null" >
        WHOLE_VEHICLE_ACTUALFEE,
      </if>
      <if test="packageOrgCode != null" >
        PACKAGE_ORG_CODE,
      </if>
      <if test="standGoodsNum != null" >
        STAND_GOODS_NUM,
      </if>
      <if test="standRequirement != null" >
        STAND_REQUIREMENT,
      </if>
      <if test="standGoodsSize != null" >
        STAND_GOODS_SIZE,
      </if>
      <if test="standGoodsVolume != null" >
        STAND_GOODS_VOLUME,
      </if>
      <if test="boxGoodsNum != null" >
        BOX_GOODS_NUM,
      </if>
      <if test="boxRequirement != null" >
        BOX_REQUIREMENT,
      </if>
      <if test="boxGoodsSize != null" >
        BOX_GOODS_SIZE,
      </if>
      <if test="boxGoodsVolume != null" >
        BOX_GOODS_VOLUME,
      </if>
      <if test="accountName != null" >
        ACCOUNT_NAME,
      </if>
      <if test="accountCode != null" >
        ACCOUNT_CODE,
      </if>
      <if test="accountBank != null" >
        ACCOUNT_BANK,
      </if>
      <if test="billWeight != null" >
        BILL_WEIGHT,
      </if>
      <if test="pickupFee != null" >
        PICKUP_FEE,
      </if>
      <if test="serviceFee != null" >
        SERVICE_FEE,
      </if>
      <if test="preArriveTime != null" >
        PRE_ARRIVE_TIME,
      </if>
      <if test="printTimes != null" >
        PRINT_TIMES,
      </if>
    </trim>
    <trim prefix="values (" suffix=")" suffixOverrides="," >
      <if test="id != null" >
        #{id,jdbcType=VARCHAR},
      </if>
      <if test="waybillNo != null" >
        #{waybillNo,jdbcType=VARCHAR},
      </if>
      <if test="orderNo != null" >
        #{orderNo,jdbcType=VARCHAR},
      </if>
      <if test="deliveryCustomerId != null" >
        #{deliveryCustomerId,jdbcType=VARCHAR},
      </if>
      <if test="deliveryCustomerCode != null" >
        #{deliveryCustomerCode,jdbcType=VARCHAR},
      </if>
      <if test="deliveryCustomerName != null" >
        #{deliveryCustomerName,jdbcType=VARCHAR},
      </if>
      <if test="deliveryCustomerMobilephone != null" >
        #{deliveryCustomerMobilephone,jdbcType=VARCHAR},
      </if>
      <if test="deliveryCustomerPhone != null" >
        #{deliveryCustomerPhone,jdbcType=VARCHAR},
      </if>
      <if test="deliveryCustomerContact != null" >
        #{deliveryCustomerContact,jdbcType=VARCHAR},
      </if>
      <if test="deliveryCustomerNationCode != null" >
        #{deliveryCustomerNationCode,jdbcType=VARCHAR},
      </if>
      <if test="deliveryCustomerProvCode != null" >
        #{deliveryCustomerProvCode,jdbcType=VARCHAR},
      </if>
      <if test="deliveryCustomerCityCode != null" >
        #{deliveryCustomerCityCode,jdbcType=VARCHAR},
      </if>
      <if test="deliveryCustomerDistCode != null" >
        #{deliveryCustomerDistCode,jdbcType=VARCHAR},
      </if>
      <if test="deliveryCustomerAddress != null" >
        #{deliveryCustomerAddress,jdbcType=VARCHAR},
      </if>
      <if test="receiveCustomerId != null" >
        #{receiveCustomerId,jdbcType=VARCHAR},
      </if>
      <if test="receiveCustomerCode != null" >
        #{receiveCustomerCode,jdbcType=VARCHAR},
      </if>
      <if test="receiveCustomerName != null" >
        #{receiveCustomerName,jdbcType=VARCHAR},
      </if>
      <if test="receiveCustomerMobilephone != null" >
        #{receiveCustomerMobilephone,jdbcType=VARCHAR},
      </if>
      <if test="receiveCustomerPhone != null" >
        #{receiveCustomerPhone,jdbcType=VARCHAR},
      </if>
      <if test="receiveCustomerContact != null" >
        #{receiveCustomerContact,jdbcType=VARCHAR},
      </if>
      <if test="receiveCustomerNationCode != null" >
        #{receiveCustomerNationCode,jdbcType=VARCHAR},
      </if>
      <if test="receiveCustomerProvCode != null" >
        #{receiveCustomerProvCode,jdbcType=VARCHAR},
      </if>
      <if test="receiveCustomerCityCode != null" >
        #{receiveCustomerCityCode,jdbcType=VARCHAR},
      </if>
      <if test="receiveCustomerDistCode != null" >
        #{receiveCustomerDistCode,jdbcType=VARCHAR},
      </if>
      <if test="receiveCustomerAddress != null" >
        #{receiveCustomerAddress,jdbcType=VARCHAR},
      </if>
      <if test="receiveOrgCode != null" >
        #{receiveOrgCode,jdbcType=VARCHAR},
      </if>
      <if test="productId != null" >
        #{productId,jdbcType=VARCHAR},
      </if>
      <if test="productCode != null" >
        #{productCode,jdbcType=VARCHAR},
      </if>
      <if test="receiveMethod != null" >
        #{receiveMethod,jdbcType=VARCHAR},
      </if>
      <if test="customerPickupOrgCode != null" >
        #{customerPickupOrgCode,jdbcType=VARCHAR},
      </if>
      <if test="loadMethod != null" >
        #{loadMethod,jdbcType=VARCHAR},
      </if>
      <if test="targetOrgCode != null" >
        #{targetOrgCode,jdbcType=VARCHAR},
      </if>
      <if test="pickupToDoor != null" >
        #{pickupToDoor,jdbcType=CHAR},
      </if>
      <if test="driverCode != null" >
        #{driverCode,jdbcType=VARCHAR},
      </if>
      <if test="pickupCentralized != null" >
        #{pickupCentralized,jdbcType=CHAR},
      </if>
      <if test="loadLineCode != null" >
        #{loadLineCode,jdbcType=VARCHAR},
      </if>
      <if test="loadOrgCode != null" >
        #{loadOrgCode,jdbcType=VARCHAR},
      </if>
      <if test="lastLoadOrgCode != null" >
        #{lastLoadOrgCode,jdbcType=VARCHAR},
      </if>
      <if test="preDepartureTime != null" >
        #{preDepartureTime,jdbcType=DATE},
      </if>
      <if test="preCustomerPickupTime != null" >
        #{preCustomerPickupTime,jdbcType=DATE},
      </if>
      <if test="carDirectDelivery != null" >
        #{carDirectDelivery,jdbcType=CHAR},
      </if>
      <if test="goodsName != null" >
        #{goodsName,jdbcType=VARCHAR},
      </if>
      <if test="goodsQtyTotal != null" >
        #{goodsQtyTotal,jdbcType=DECIMAL},
      </if>
      <if test="goodsWeightTotal != null" >
        #{goodsWeightTotal,jdbcType=DECIMAL},
      </if>
      <if test="goodsVolumeTotal != null" >
        #{goodsVolumeTotal,jdbcType=DECIMAL},
      </if>
      <if test="goodsSize != null" >
        #{goodsSize,jdbcType=VARCHAR},
      </if>
      <if test="goodsTypeCode != null" >
        #{goodsTypeCode,jdbcType=VARCHAR},
      </if>
      <if test="preciousGoods != null" >
        #{preciousGoods,jdbcType=CHAR},
      </if>
      <if test="specialShapedGoods != null" >
        #{specialShapedGoods,jdbcType=CHAR},
      </if>
      <if test="outerNotes != null" >
        #{outerNotes,jdbcType=VARCHAR},
      </if>
      <if test="innerNotes != null" >
        #{innerNotes,jdbcType=VARCHAR},
      </if>
      <if test="goodsPackage != null" >
        #{goodsPackage,jdbcType=VARCHAR},
      </if>
      <if test="insuranceAmount != null" >
        #{insuranceAmount,jdbcType=DECIMAL},
      </if>
      <if test="insuranceRate != null" >
        #{insuranceRate,jdbcType=DECIMAL},
      </if>
      <if test="insuranceFee != null" >
        #{insuranceFee,jdbcType=DECIMAL},
      </if>
      <if test="codAmount != null" >
        #{codAmount,jdbcType=DECIMAL},
      </if>
      <if test="codRate != null" >
        #{codRate,jdbcType=DECIMAL},
      </if>
      <if test="codFee != null" >
        #{codFee,jdbcType=DECIMAL},
      </if>
      <if test="refundType != null" >
        #{refundType,jdbcType=VARCHAR},
      </if>
      <if test="returnBillType != null" >
        #{returnBillType,jdbcType=VARCHAR},
      </if>
      <if test="secretPrepaid != null" >
        #{secretPrepaid,jdbcType=CHAR},
      </if>
      <if test="toPayAmount != null" >
        #{toPayAmount,jdbcType=DECIMAL},
      </if>
      <if test="prePayAmount != null" >
        #{prePayAmount,jdbcType=DECIMAL},
      </if>
      <if test="deliveryGoodsFee != null" >
        #{deliveryGoodsFee,jdbcType=DECIMAL},
      </if>
      <if test="otherFee != null" >
        #{otherFee,jdbcType=DECIMAL},
      </if>
      <if test="packageFee != null" >
        #{packageFee,jdbcType=DECIMAL},
      </if>
      <if test="promotionsFee != null" >
        #{promotionsFee,jdbcType=DECIMAL},
      </if>
      <if test="billingType != null" >
        #{billingType,jdbcType=VARCHAR},
      </if>
      <if test="unitPrice != null" >
        #{unitPrice,jdbcType=DECIMAL},
      </if>
      <if test="transportFee != null" >
        #{transportFee,jdbcType=DECIMAL},
      </if>
      <if test="valueAddFee != null" >
        #{valueAddFee,jdbcType=DECIMAL},
      </if>
      <if test="paidMethod != null" >
        #{paidMethod,jdbcType=VARCHAR},
      </if>
      <if test="arriveType != null" >
        #{arriveType,jdbcType=VARCHAR},
      </if>
      <if test="active != null" >
        #{active,jdbcType=VARCHAR},
      </if>
      <if test="forbiddenLine != null" >
        #{forbiddenLine,jdbcType=CHAR},
      </if>
      <if test="freightMethod != null" >
        #{freightMethod,jdbcType=VARCHAR},
      </if>
      <if test="flightShift != null" >
        #{flightShift,jdbcType=VARCHAR},
      </if>
      <if test="totalFee != null" >
        #{totalFee,jdbcType=DECIMAL},
      </if>
      <if test="promotionsCode != null" >
        #{promotionsCode,jdbcType=VARCHAR},
      </if>
      <if test="createTime != null" >
        #{createTime,jdbcType=DATE},
      </if>
      <if test="modifyTime != null" >
        #{modifyTime,jdbcType=DATE},
      </if>
      <if test="billTime != null" >
        #{billTime,jdbcType=DATE},
      </if>
      <if test="createUserCode != null" >
        #{createUserCode,jdbcType=VARCHAR},
      </if>
      <if test="modifyUserCode != null" >
        #{modifyUserCode,jdbcType=VARCHAR},
      </if>
      <if test="createOrgCode != null" >
        #{createOrgCode,jdbcType=VARCHAR},
      </if>
      <if test="modifyOrgCode != null" >
        #{modifyOrgCode,jdbcType=VARCHAR},
      </if>
      <if test="refId != null" >
        #{refId,jdbcType=VARCHAR},
      </if>
      <if test="refCode != null" >
        #{refCode,jdbcType=VARCHAR},
      </if>
      <if test="currencyCode != null" >
        #{currencyCode,jdbcType=VARCHAR},
      </if>
      <if test="isWholeVehicle != null" >
        #{isWholeVehicle,jdbcType=CHAR},
      </if>
      <if test="wholeVehicleAppfee != null" >
        #{wholeVehicleAppfee,jdbcType=DECIMAL},
      </if>
      <if test="wholeVehicleActualfee != null" >
        #{wholeVehicleActualfee,jdbcType=DECIMAL},
      </if>
      <if test="packageOrgCode != null" >
        #{packageOrgCode,jdbcType=VARCHAR},
      </if>
      <if test="standGoodsNum != null" >
        #{standGoodsNum,jdbcType=DECIMAL},
      </if>
      <if test="standRequirement != null" >
        #{standRequirement,jdbcType=VARCHAR},
      </if>
      <if test="standGoodsSize != null" >
        #{standGoodsSize,jdbcType=VARCHAR},
      </if>
      <if test="standGoodsVolume != null" >
        #{standGoodsVolume,jdbcType=DECIMAL},
      </if>
      <if test="boxGoodsNum != null" >
        #{boxGoodsNum,jdbcType=DECIMAL},
      </if>
      <if test="boxRequirement != null" >
        #{boxRequirement,jdbcType=VARCHAR},
      </if>
      <if test="boxGoodsSize != null" >
        #{boxGoodsSize,jdbcType=VARCHAR},
      </if>
      <if test="boxGoodsVolume != null" >
        #{boxGoodsVolume,jdbcType=DECIMAL},
      </if>
      <if test="accountName != null" >
        #{accountName,jdbcType=VARCHAR},
      </if>
      <if test="accountCode != null" >
        #{accountCode,jdbcType=VARCHAR},
      </if>
      <if test="accountBank != null" >
        #{accountBank,jdbcType=VARCHAR},
      </if>
      <if test="billWeight != null" >
        #{billWeight,jdbcType=DECIMAL},
      </if>
      <if test="pickupFee != null" >
        #{pickupFee,jdbcType=DECIMAL},
      </if>
      <if test="serviceFee != null" >
        #{serviceFee,jdbcType=DECIMAL},
      </if>
      <if test="preArriveTime != null" >
        #{preArriveTime,jdbcType=DATE},
      </if>
      <if test="printTimes != null" >
        #{printTimes,jdbcType=DECIMAL},
      </if>
    </trim>
  </insert>

  <update id="updateByPrimaryKey" parameterType="com.deppon.foss.module.pickup.waybill.shared.domain.WaybillOfflineEntity" >
    update PKP.T_SRV_WAYBILL_OFFLINE
    set WAYBILL_NO = #{waybillNo,jdbcType=VARCHAR},
      ORDER_NO = #{orderNo,jdbcType=VARCHAR},
      DELIVERY_CUSTOMER_ID = #{deliveryCustomerId,jdbcType=VARCHAR},
      DELIVERY_CUSTOMER_CODE = #{deliveryCustomerCode,jdbcType=VARCHAR},
      DELIVERY_CUSTOMER_NAME = #{deliveryCustomerName,jdbcType=VARCHAR},
      DELIVERY_CUSTOMER_MOBILEPHONE = #{deliveryCustomerMobilephone,jdbcType=VARCHAR},
      DELIVERY_CUSTOMER_PHONE = #{deliveryCustomerPhone,jdbcType=VARCHAR},
      DELIVERY_CUSTOMER_CONTACT = #{deliveryCustomerContact,jdbcType=VARCHAR},
      DELIVERY_CUSTOMER_NATION_CODE = #{deliveryCustomerNationCode,jdbcType=VARCHAR},
      DELIVERY_CUSTOMER_PROV_CODE = #{deliveryCustomerProvCode,jdbcType=VARCHAR},
      DELIVERY_CUSTOMER_CITY_CODE = #{deliveryCustomerCityCode,jdbcType=VARCHAR},
      DELIVERY_CUSTOMER_DIST_CODE = #{deliveryCustomerDistCode,jdbcType=VARCHAR},
      DELIVERY_CUSTOMER_ADDRESS = #{deliveryCustomerAddress,jdbcType=VARCHAR},
      RECEIVE_CUSTOMER_ID = #{receiveCustomerId,jdbcType=VARCHAR},
      RECEIVE_CUSTOMER_CODE = #{receiveCustomerCode,jdbcType=VARCHAR},
      RECEIVE_CUSTOMER_NAME = #{receiveCustomerName,jdbcType=VARCHAR},
      RECEIVE_CUSTOMER_MOBILEPHONE = #{receiveCustomerMobilephone,jdbcType=VARCHAR},
      RECEIVE_CUSTOMER_PHONE = #{receiveCustomerPhone,jdbcType=VARCHAR},
      RECEIVE_CUSTOMER_CONTACT = #{receiveCustomerContact,jdbcType=VARCHAR},
      RECEIVE_CUSTOMER_NATION_CODE = #{receiveCustomerNationCode,jdbcType=VARCHAR},
      RECEIVE_CUSTOMER_PROV_CODE = #{receiveCustomerProvCode,jdbcType=VARCHAR},
      RECEIVE_CUSTOMER_CITY_CODE = #{receiveCustomerCityCode,jdbcType=VARCHAR},
      RECEIVE_CUSTOMER_DIST_CODE = #{receiveCustomerDistCode,jdbcType=VARCHAR},
      RECEIVE_CUSTOMER_ADDRESS = #{receiveCustomerAddress,jdbcType=VARCHAR},
      RECEIVE_ORG_CODE = #{receiveOrgCode,jdbcType=VARCHAR},
      PRODUCT_ID = #{productId,jdbcType=VARCHAR},
      PRODUCT_CODE = #{productCode,jdbcType=VARCHAR},
      RECEIVE_METHOD = #{receiveMethod,jdbcType=VARCHAR},
      CUSTOMER_PICKUP_ORG_CODE = #{customerPickupOrgCode,jdbcType=VARCHAR},
      LOAD_METHOD = #{loadMethod,jdbcType=VARCHAR},
      TARGET_ORG_CODE = #{targetOrgCode,jdbcType=VARCHAR},
      PICKUP_TO_DOOR = #{pickupToDoor,jdbcType=CHAR},
      DRIVER_CODE = #{driverCode,jdbcType=VARCHAR},
      PICKUP_CENTRALIZED = #{pickupCentralized,jdbcType=CHAR},
      LOAD_LINE_CODE = #{loadLineCode,jdbcType=VARCHAR},
      LOAD_ORG_CODE = #{loadOrgCode,jdbcType=VARCHAR},
      LAST_LOAD_ORG_CODE = #{lastLoadOrgCode,jdbcType=VARCHAR},
      PRE_DEPARTURE_TIME = #{preDepartureTime,jdbcType=DATE},
      PRE_CUSTOMER_PICKUP_TIME = #{preCustomerPickupTime,jdbcType=DATE},
      CAR_DIRECT_DELIVERY = #{carDirectDelivery,jdbcType=CHAR},
      GOODS_NAME = #{goodsName,jdbcType=VARCHAR},
      GOODS_QTY_TOTAL = #{goodsQtyTotal,jdbcType=DECIMAL},
      GOODS_WEIGHT_TOTAL = #{goodsWeightTotal,jdbcType=DECIMAL},
      GOODS_VOLUME_TOTAL = #{goodsVolumeTotal,jdbcType=DECIMAL},
      GOODS_SIZE = #{goodsSize,jdbcType=VARCHAR},
      GOODS_TYPE_CODE = #{goodsTypeCode,jdbcType=VARCHAR},
      PRECIOUS_GOODS = #{preciousGoods,jdbcType=CHAR},
      SPECIAL_SHAPED_GOODS = #{specialShapedGoods,jdbcType=CHAR},
      OUTER_NOTES = #{outerNotes,jdbcType=VARCHAR},
      INNER_NOTES = #{innerNotes,jdbcType=VARCHAR},
      GOODS_PACKAGE = #{goodsPackage,jdbcType=VARCHAR},
      INSURANCE_AMOUNT = #{insuranceAmount,jdbcType=DECIMAL},
      INSURANCE_RATE = #{insuranceRate,jdbcType=DECIMAL},
      INSURANCE_FEE = #{insuranceFee,jdbcType=DECIMAL},
      COD_AMOUNT = #{codAmount,jdbcType=DECIMAL},
      COD_RATE = #{codRate,jdbcType=DECIMAL},
      COD_FEE = #{codFee,jdbcType=DECIMAL},
      REFUND_TYPE = #{refundType,jdbcType=VARCHAR},
      RETURN_BILL_TYPE = #{returnBillType,jdbcType=VARCHAR},
      SECRET_PREPAID = #{secretPrepaid,jdbcType=CHAR},
      TO_PAY_AMOUNT = #{toPayAmount,jdbcType=DECIMAL},
      PRE_PAY_AMOUNT = #{prePayAmount,jdbcType=DECIMAL},
      DELIVERY_GOODS_FEE = #{deliveryGoodsFee,jdbcType=DECIMAL},
      OTHER_FEE = #{otherFee,jdbcType=DECIMAL},
      PACKAGE_FEE = #{packageFee,jdbcType=DECIMAL},
      PROMOTIONS_FEE = #{promotionsFee,jdbcType=DECIMAL},
      BILLING_TYPE = #{billingType,jdbcType=VARCHAR},
      UNIT_PRICE = #{unitPrice,jdbcType=DECIMAL},
      TRANSPORT_FEE = #{transportFee,jdbcType=DECIMAL},
      VALUE_ADD_FEE = #{valueAddFee,jdbcType=DECIMAL},
      PAID_METHOD = #{paidMethod,jdbcType=VARCHAR},
      ARRIVE_TYPE = #{arriveType,jdbcType=VARCHAR},
      ACTIVE = #{active,jdbcType=VARCHAR},
      FORBIDDEN_LINE = #{forbiddenLine,jdbcType=CHAR},
      FREIGHT_METHOD = #{freightMethod,jdbcType=VARCHAR},
      FLIGHT_SHIFT = #{flightShift,jdbcType=VARCHAR},
      TOTAL_FEE = #{totalFee,jdbcType=DECIMAL},
      PROMOTIONS_CODE = #{promotionsCode,jdbcType=VARCHAR},
      CREATE_TIME = #{createTime,jdbcType=DATE},
      MODIFY_TIME = #{modifyTime,jdbcType=DATE},
      BILL_TIME = #{billTime,jdbcType=DATE},
      CREATE_USER_CODE = #{createUserCode,jdbcType=VARCHAR},
      MODIFY_USER_CODE = #{modifyUserCode,jdbcType=VARCHAR},
      CREATE_ORG_CODE = #{createOrgCode,jdbcType=VARCHAR},
      MODIFY_ORG_CODE = #{modifyOrgCode,jdbcType=VARCHAR},
      REF_ID = #{refId,jdbcType=VARCHAR},
      REF_CODE = #{refCode,jdbcType=VARCHAR},
      CURRENCY_CODE = #{currencyCode,jdbcType=VARCHAR},
      IS_WHOLE_VEHICLE = #{isWholeVehicle,jdbcType=CHAR},
      WHOLE_VEHICLE_APPFEE = #{wholeVehicleAppfee,jdbcType=DECIMAL},
      WHOLE_VEHICLE_ACTUALFEE = #{wholeVehicleActualfee,jdbcType=DECIMAL},
      PACKAGE_ORG_CODE = #{packageOrgCode,jdbcType=VARCHAR},
      STAND_GOODS_NUM = #{standGoodsNum,jdbcType=DECIMAL},
      STAND_REQUIREMENT = #{standRequirement,jdbcType=VARCHAR},
      STAND_GOODS_SIZE = #{standGoodsSize,jdbcType=VARCHAR},
      STAND_GOODS_VOLUME = #{standGoodsVolume,jdbcType=DECIMAL},
      BOX_GOODS_NUM = #{boxGoodsNum,jdbcType=DECIMAL},
      BOX_REQUIREMENT = #{boxRequirement,jdbcType=VARCHAR},
      BOX_GOODS_SIZE = #{boxGoodsSize,jdbcType=VARCHAR},
      BOX_GOODS_VOLUME = #{boxGoodsVolume,jdbcType=DECIMAL},
      ACCOUNT_NAME = #{accountName,jdbcType=VARCHAR},
      ACCOUNT_CODE = #{accountCode,jdbcType=VARCHAR},
      ACCOUNT_BANK = #{accountBank,jdbcType=VARCHAR},
      BILL_WEIGHT = #{billWeight,jdbcType=DECIMAL},
      PICKUP_FEE = #{pickupFee,jdbcType=DECIMAL},
      SERVICE_FEE = #{serviceFee,jdbcType=DECIMAL},
      PRE_ARRIVE_TIME = #{preArriveTime,jdbcType=DATE},
      PRINT_TIMES = #{printTimes,jdbcType=DECIMAL}
    where ID = #{id,jdbcType=VARCHAR}
  </update>
  
  <update id="updateWaybillPrintTimeOffLine" parameterType="java.lang.String">
		update PKP.T_SRV_WAYBILL_OFFLINE
		set
		PRINT_TIMES = #{printTimes,jdbcType=DECIMAL}
		where WAYBILL_NO= #{waybillNo,jdbcType=VARCHAR}
  </update>
  
  <select id="getWaybillOfflines" resultMap="BaseResultMap" parameterType="com.deppon.foss.module.pickup.waybill.shared.dto.WaybillOfflineDto" >
    select 
		<include refid="Base_Column_List" />
	        from PKP.T_SRV_WAYBILL_OFFLINE p
	    <![CDATA[    
	            where  p.BILL_TIME >=  #{billStartTime} and p.BILL_TIME <= #{billEndTime}
	    ]]>  
	    <![CDATA[    
	            and  p.CREATE_TIME >=  #{createStartTime} and p.CREATE_TIME <= #{createEndTime}
	    ]]> 
	    <if test="waybillOfflineEntity.receiveOrgCode != null and waybillOfflineEntity.receiveOrgCode !='' ">
				and p.RECEIVE_ORG_CODE = #{waybillOfflineEntity.receiveOrgCode,jdbcType=VARCHAR}
		</if>
		<if test="waybillOfflineEntity.productCode != 'all' ">
				and p.product_code = #{waybillOfflineEntity.productCode,jdbcType=VARCHAR}
		</if>
		<if test="waybillOfflineEntity.active != null">
				and p.active = #{waybillOfflineEntity.active,jdbcType=VARCHAR}
		</if>
		<if test="waybillOfflineEntity.createUserCode != null and waybillOfflineEntity.createUserCode !='' ">
				and p.create_user_code = #{waybillOfflineEntity.createUserCode,jdbcType=VARCHAR}
		</if>
		<if test="waybillOfflineEntity.createOrgCode != null and waybillOfflineEntity.createOrgCode !='' ">
				and p.create_org_code = #{waybillOfflineEntity.createOrgCode,jdbcType=VARCHAR}
		</if>
		<if test="mixNo !=null and mixNo != '' ">
				and p.WAYBILL_NO = #{mixNo,jdbcType=VARCHAR} or p.ORDER_NO = #{mixNo,jdbcType=VARCHAR}
		</if> 
	                order by p.BILL_TIME asc           
  </select>
  
  <select id="queryOffine" resultMap="BaseResultMap" parameterType="java.lang.String" >
	  select 
		<include refid="Base_Column_List" />
	        from PKP.T_SRV_WAYBILL_OFFLINE p
	      <![CDATA[  
	        where p.WAYBILL_NO = #{mixNo,jdbcType=VARCHAR} or p.ORDER_NO = #{mixNo,jdbcType=VARCHAR}
	    ]]>     
  </select>
  <select id="countOffineActiveWaybill" resultType="java.lang.Integer" parameterType="java.lang.String" >
	  select count(1) as num from PKP.T_SRV_WAYBILL_OFFLINE p where p.ACTIVE='Y'
  </select>
</mapper>